recogaud/__init__.py
recogaud/recogaud.py
recogaud-0.2.dist-info/METADATA
recogaud-0.2.dist-info/WHEEL
recogaud-0.2.dist-info/top_level.txt
recogaud-0.2.dist-info/RECORD
